move_alarm/__init__.py
move_alarm/app.py
move_alarm/assets/basementfunk.wav
move_alarm/assets/fresh-pop-alert.wav
move_alarm/components/__init__.py
move_alarm/components/alarm.py
move_alarm/components/sounds.py
move_alarm/contexts/__init__.py
move_alarm/contexts/use_context.py
move_alarm/datatypes/__init__.py
move_alarm/datatypes/alarm.py
move_alarm/datatypes/config.py
move_alarm/datatypes/contexts.py
move_alarm/datatypes/oauth.py
move_alarm/datatypes/sounds.py
move_alarm/utils/__init__.py
move_alarm/utils/api_calls.py
move_alarm/utils/config.py
move_alarm/utils/helpers.py
move_alarm/utils/oauth.py
move_alarm-1.0.1.dist-info/LICENSE
move_alarm-1.0.1.dist-info/METADATA
move_alarm-1.0.1.dist-info/WHEEL
move_alarm-1.0.1.dist-info/entry_points.txt
move_alarm-1.0.1.dist-info/RECORD
