Metadata-Version: 2.3
Name: move-alarm
Version: 1.0.1
Summary: An alarm designed to remind you to be more active!
License: LICENSE
Author: DevDolphin7
Author-email: devdolphin7@outlook.com
Requires-Python: >=3.10
Classifier: License :: Other/Proprietary License
Classifier: Programming Language :: Python :: 3
Classifier: Programming Language :: Python :: 3.10
Classifier: Programming Language :: Python :: 3.11
Classifier: Programming Language :: Python :: 3.12
Classifier: Programming Language :: Python :: 3.13
Requires-Dist: python-dotenv (>=1.0.1,<2.0.0)
Requires-Dist: requests (>=2.32.3,<3.0.0)
Requires-Dist: simpleaudio (>=1.0.4,<2.0.0)
Requires-Dist: types-requests (>=2.32.0.20241016,<3.0.0.0)
